dep_lerng/AttentionBlocks.py
dep_lerng/ClassifierNet.py
dep_lerng/Dataset.py
dep_lerng/ResBlock.py
dep_lerng/ResNet.py
dep_lerng/UtilityBlocks.py
dep_lerng/__init__.py
dep_lerng/model_init.py
dep_lerng-0.32.dist-info/METADATA
dep_lerng-0.32.dist-info/WHEEL
dep_lerng-0.32.dist-info/top_level.txt
dep_lerng-0.32.dist-info/RECORD
