Metadata-Version: 2.1
Name: dep-lerng
Version: 0.32
Summary: Testing installation of Package
Home-page: https://github.com/Kitty2xl/dep_lerng
Author: auth
Author-email: kitty2xl41@email.com
License: MIT
